os_dev/__init__.py
os_dev/os_dev.py
os_dev-0.0.14.dist-info/LICENSE
os_dev-0.0.14.dist-info/METADATA
os_dev-0.0.14.dist-info/WHEEL
os_dev-0.0.14.dist-info/top_level.txt
os_dev-0.0.14.dist-info/RECORD
