Metadata-Version: 2.1
Name: os-dev
Version: 0.0.14
Summary: Gives you tools to make an OS in Python
Author: Bodie Sevcik
Author-email: bodei11007@gmail.com
Keywords: python,py,os,dev,system,operating
Classifier: Development Status :: 1 - Planning
Classifier: Intended Audience :: Developers
Classifier: Programming Language :: Python :: 3
Classifier: Operating System :: Unix
Classifier: Operating System :: MacOS :: MacOS X
Classifier: Operating System :: Microsoft :: Windows
License-File: LICENSE
